montague/__init__.py
montague/ast.py
montague/exceptions.py
montague/interpreter.py
montague/main.py
montague/montague.py
montague/parser.py
montague/translator.py
montague/resources/fragment.json
test/__init__.py
test/test_ast.py
test/test_interpreter.py
test/test_main.py
test/test_montague.py
test/test_parser.py
test/test_translator.py
montague_nlu-0.1.6.dist-info/LICENSE
montague_nlu-0.1.6.dist-info/METADATA
montague_nlu-0.1.6.dist-info/WHEEL
montague_nlu-0.1.6.dist-info/entry_points.txt
montague_nlu-0.1.6.dist-info/top_level.txt
montague_nlu-0.1.6.dist-info/RECORD
