Metadata-Version: 2.1
Name: montague-nlu
Version: 0.1.6
Summary: Natural language understanding system
Home-page: UNKNOWN
Author: Ian Fisher
Author-email: iafisher@protonmail.com
License: MIT
Project-URL: Source, https://github.com/iafisher/montague
Platform: UNKNOWN
Classifier: Programming Language :: Python :: 3
Classifier: License :: OSI Approved :: MIT License
Classifier: Natural Language :: English
Classifier: Topic :: Text Processing :: Linguistic
Classifier: Topic :: Scientific/Engineering :: Artificial Intelligence
Requires-Dist: lark-parser (==0.6.4)
